na_seq-0.3.5.dist-info/METADATA
na_seq-0.3.5.dist-info/WHEEL
na_seq-0.3.5.dist-info/licenses/PYPI_LICENSE
na_seq/__init__.py
na_seq/na_seq.abi3.so
na_seq-0.3.5.dist-info/RECORD
