Metadata-Version: 2.4
Name: na_seq
Version: 0.3.5
Classifier: Programming Language :: Rust
Classifier: Programming Language :: Python :: Implementation :: CPython
Classifier: Programming Language :: Python :: Implementation :: PyPy
License-File: PYPI_LICENSE
Summary: DNA, RNA, and amino acid sequence types and functions
Author-email: David O'Connor <the_alchemist@fastmail.com>
Requires-Python: >=3.10
